Monisha/__init__.py
Monisha/exceptions/__init__.py
Monisha/exceptions/exceptions.py
Monisha/functions/__init__.py
Monisha/functions/collections.py
Monisha/functions/function01.py
Monisha/functions/function02.py
Monisha/functions/function03.py
Monisha/functions/function04.py
Monisha/functions/function05.py
Monisha/functions/function06.py
Monisha/functions/function07.py
Monisha/functions/function08.py
Monisha/functions/function09.py
Monisha/functions/function10.py
Monisha/functions/function11.py
Monisha/functions/function12.py
Monisha/functions/function13.py
Monisha/functions/function14.py
Monisha/functions/function15.py
Monisha/functions/function16.py
Monisha/functions/function17.py
Monisha/functions/function18.py
Monisha/functions/function19.py
Monisha/functions/function20.py
Monisha/functions/function21.py
Monisha/functions/function22.py
Monisha/functions/function23.py
Monisha/functions/function24.py
Monisha/functions/function25.py
Monisha/functions/function26.py
Monisha/functions/function27.py
Monisha/functions/function28.py
Monisha/functions/function29.py
Monisha/functions/function30.py
Monisha/functions/function31.py
Monisha/functions/function33.py
Monisha/functions/function35.py
Monisha/scripts/__init__.py
Monisha/scripts/script01.py
Monisha/scripts/script02.py
Monisha/scripts/script03.py
Monisha/scripts/script04.py
Monisha/scripts/script05.py
Monisha/scripts/script06.py
monisha-0.0.115.dist-info/METADATA
monisha-0.0.115.dist-info/WHEEL
monisha-0.0.115.dist-info/top_level.txt
monisha-0.0.115.dist-info/RECORD
