Metadata-Version: 2.4
Name: monisha
Version: 0.0.115
Summary: ㅤ
Author: Monisha
License: MIT
Keywords: apps,python,extensions
Classifier: Natural Language :: English
Classifier: Intended Audience :: Developers
Classifier: Operating System :: OS Independent
Classifier: Programming Language :: Python :: 3.10
Classifier: Programming Language :: Python :: 3.11
Classifier: Programming Language :: Python :: 3.12
Classifier: Programming Language :: Python :: 3.13
Classifier: Programming Language :: Python :: 3.14
Requires-Python: ~=3.10
Requires-Dist: pytz
Requires-Dist: arrow
Requires-Dist: psutil
Requires-Dist: pillow
Requires-Dist: hachoir
Requires-Dist: requests
Requires-Dist: beautifulsoup4
Dynamic: author
Dynamic: classifier
Dynamic: description
Dynamic: description-content-type
Dynamic: keywords
Dynamic: license
Dynamic: requires-dist
Dynamic: requires-python
Dynamic: summary
